engagespark/__init__.py
engagespark/utils.py
engagespark-0.1.dist-info/METADATA
engagespark-0.1.dist-info/RECORD
engagespark-0.1.dist-info/WHEEL
engagespark-0.1.dist-info/top_level.txt
engagespark-0.1.dist-info/zip-safe
